slaac_resolver/__Init__.py
slaac_resolver/cli.py
slaac_resolver/core.py
slaac_resolver-0.1.0.dist-info/licenses/LICENSE
slaac_resolver-0.1.0.dist-info/METADATA
slaac_resolver-0.1.0.dist-info/WHEEL
slaac_resolver-0.1.0.dist-info/entry_points.txt
slaac_resolver-0.1.0.dist-info/top_level.txt
slaac_resolver-0.1.0.dist-info/RECORD
