Metadata-Version: 2.4
Name: slaac-resolver
Version: 0.1.0
Summary: Discover SLAAC IPv6 neighbors and resolve their names via mDNS (Avahi)
Author-email: Carlos Junior <cjuniorfox@gmail.com>
License: GNU General Public License v3.0 (GPLv3)
Project-URL: Homepage, https://github.com/cjuniorfox/slaac-resolver
Keywords: slaac,ipv6,mdns,avahi,networking
Requires-Python: >=3.7
License-File: LICENSE
Dynamic: license-file
